{
	"principalNote":{
		"root": {
			"type": "dialog",
			"fragments": [{
				"tag": "Note",
				"msn": "Principal's office."
			}]
		}
	},
	"principalDoor":{
		"root": {
			"type": "dialog",
			"fragments": [{
				"tag": "You",
				"msn": "Looks like nobody's there."
			}]
		}
	},
	"stairsToCorridor": {
		"root": {
			"type": "event",
			"event": {
				"name": "move camera",
				"key": "corridor"
			}
		}
	},
	"stairsToPlayground": {
		"root": {
			"type": "event",
			"event": {
				"name": "move camera",
				"key": "endDay"
			}
		}
	}
}